[
  {
    "id": "1da6e7ee-161d-40d0-9606-2f50d75e63ad",
    "timestamp": "2025-12-02T18:50:27.025Z",
    "email": "trtr@yt.uy",
    "sessionId": "sess_1764701416800_0bna16n8x",
    "userAgent": "Mozilla/5.0 (Linux; Android 10; K) AppleWebKit/537.36 (KHTML, like Gecko) Chrome/142.0.0.0 Mobile Safari/537.36"
  },
  {
    "id": "86ab4a10-7042-4490-b69e-f897635b90ee",
    "timestamp": "2025-12-16T19:20:25.184Z",
    "email": "haga@gmail.com",
    "sessionId": "sess_1765912793735_xpmkeynt9",
    "userAgent": "Mozilla/5.0 (Linux; Android 10; K) AppleWebKit/537.36 (KHTML, like Gecko) Chrome/143.0.0.0 Mobile Safari/537.36"
  }
]